{
  "class": "Elf",
  "document_link": "https://www.elastic.co/guide/en/ecs/current/ecs-elf.html",
  "key": "elf",
  "properties": {
    "architecture": {
      "types": [
        "nullable",
        "string"
      ]
    },
    "byte_order": {
      "types": [
        "nullable",
        "string"
      ]
    },
    "cpu_type": {
      "types": [
        "nullable",
        "string"
      ]
    },
    "creation_date": {
      "types": [
        "nullable",
        "Carbon\\Carbon"
      ],
      "cast": "toIso8601ZuluString"
    },
    "exports": {
      "types": [
        "nullable",
        "Hamidrezaniazi\\Pecs\\Properties\\ValueList"
      ],
      "cast": "toArray"
    },
    "go_import_hash": {
      "types": [
        "nullable",
        "string"
      ]
    },
    "go_imports": {
      "types": [
        "nullable",
        "Hamidrezaniazi\\Pecs\\Properties\\ValueList"
      ],
      "cast": "toArray"
    },
    "go_imports_names_entropy": {
      "types": [
        "nullable",
        "int"
      ]
    },
    "go_imports_names_var_entropy": {
      "types": [
        "nullable",
        "int"
      ]
    },
    "go_stripped": {
      "types": [
        "nullable",
        "bool"
      ]
    },
    "header.abi_version": {
      "types": [
        "nullable",
        "string"
      ]
    },
    "header.class": {
      "types": [
        "nullable",
        "string"
      ]
    },
    "header.data": {
      "types": [
        "nullable",
        "string"
      ]
    },
    "header.entrypoint": {
      "types": [
        "nullable",
        "int"
      ]
    },
    "header.object_version": {
      "types": [
        "nullable",
        "string"
      ]
    },
    "header.os_abi": {
      "types": [
        "nullable",
        "string"
      ]
    },
    "import_hash": {
      "types": [
        "nullable",
        "string"
      ]
    },
    "imports": {
      "types": [
        "nullable",
        "Hamidrezaniazi\\Pecs\\Properties\\ValueList"
      ],
      "cast": "toArray"
    },
    "imports_names_entropy": {
      "types": [
        "nullable",
        "int"
      ]
    },
    "imports_names_var_entropy": {
      "types": [
        "nullable",
        "int"
      ]
    },
    "sections": {
      "types": [
        "nullable",
        "Hamidrezaniazi\\Pecs\\Properties\\Listables\\ElfSectionList"
      ],
      "cast": "toArray"
    },
    "segments": {
      "types": [
        "nullable",
        "Hamidrezaniazi\\Pecs\\Properties\\Listables\\ElfSegmentList"
      ],
      "cast": "toArray"
    },
    "shared_libraries": {
      "types": [
        "nullable",
        "Hamidrezaniazi\\Pecs\\Properties\\ValueList"
      ],
      "cast": "toArray"
    },
    "telfhash": {
      "types": [
        "nullable",
        "string"
      ]
    }
  }
}